odoo/addons/helpdesk_mgmt/README.rst
odoo/addons/helpdesk_mgmt/__init__.py
odoo/addons/helpdesk_mgmt/__manifest__.py
odoo/addons/helpdesk_mgmt/controllers/__init__.py
odoo/addons/helpdesk_mgmt/controllers/main.py
odoo/addons/helpdesk_mgmt/controllers/myaccount.py
odoo/addons/helpdesk_mgmt/data/helpdesk_data.xml
odoo/addons/helpdesk_mgmt/demo/helpdesk_demo.xml
odoo/addons/helpdesk_mgmt/i18n/ca.po
odoo/addons/helpdesk_mgmt/i18n/ca_ES.po
odoo/addons/helpdesk_mgmt/i18n/de.po
odoo/addons/helpdesk_mgmt/i18n/es.po
odoo/addons/helpdesk_mgmt/i18n/es_AR.po
odoo/addons/helpdesk_mgmt/i18n/fr.po
odoo/addons/helpdesk_mgmt/i18n/helpdesk_mgmt.pot
odoo/addons/helpdesk_mgmt/i18n/hu.po
odoo/addons/helpdesk_mgmt/i18n/it.po
odoo/addons/helpdesk_mgmt/i18n/lv.po
odoo/addons/helpdesk_mgmt/i18n/lv_LV.po
odoo/addons/helpdesk_mgmt/i18n/nl.po
odoo/addons/helpdesk_mgmt/i18n/nl_NL.po
odoo/addons/helpdesk_mgmt/i18n/pl.po
odoo/addons/helpdesk_mgmt/i18n/pt.po
odoo/addons/helpdesk_mgmt/i18n/pt_BR.po
odoo/addons/helpdesk_mgmt/i18n/ru.po
odoo/addons/helpdesk_mgmt/i18n/sk.po
odoo/addons/helpdesk_mgmt/i18n/sv.po
odoo/addons/helpdesk_mgmt/i18n/tr.po
odoo/addons/helpdesk_mgmt/migrations/18.0.1.7.0/post-migration.py
odoo/addons/helpdesk_mgmt/models/__init__.py
odoo/addons/helpdesk_mgmt/models/helpdesk_ticket.py
odoo/addons/helpdesk_mgmt/models/helpdesk_ticket_category.py
odoo/addons/helpdesk_mgmt/models/helpdesk_ticket_channel.py
odoo/addons/helpdesk_mgmt/models/helpdesk_ticket_stage.py
odoo/addons/helpdesk_mgmt/models/helpdesk_ticket_tag.py
odoo/addons/helpdesk_mgmt/models/helpdesk_ticket_team.py
odoo/addons/helpdesk_mgmt/models/ir_http.py
odoo/addons/helpdesk_mgmt/models/res_company.py
odoo/addons/helpdesk_mgmt/models/res_config_settings.py
odoo/addons/helpdesk_mgmt/models/res_partner.py
odoo/addons/helpdesk_mgmt/models/res_users.py
odoo/addons/helpdesk_mgmt/readme/CONFIGURE.md
odoo/addons/helpdesk_mgmt/readme/CONTRIBUTORS.md
odoo/addons/helpdesk_mgmt/readme/DESCRIPTION.md
odoo_addon_helpdesk_mgmt-18.0.1.16.2.dist-info/METADATA
odoo_addon_helpdesk_mgmt-18.0.1.16.2.dist-info/WHEEL
odoo_addon_helpdesk_mgmt-18.0.1.16.2.dist-info/top_level.txt
odoo_addon_helpdesk_mgmt-18.0.1.16.2.dist-info/RECORD
