Metadata-Version: 2.1
Name: odoo-addon-helpdesk_mgmt
Version: 18.0.1.16.2
Requires-Python: >=3.10
Requires-Dist: odoo==18.0.*
Summary: Helpdesk
Home-page: https://github.com/OCA/helpdesk
License: AGPL-3
Author: AdaptiveCity, Tecnativa, ForgeFlow, C2i Change 2 Improve, Domatix, Factor Libre, SDi Soluciones, Odoo Community Association (OCA)
Author-email: support@odoo-community.org
Classifier: Programming Language :: Python
Classifier: Framework :: Odoo
Classifier: Framework :: Odoo :: 18.0
Classifier: License :: OSI Approved :: GNU Affero General Public License v3
Classifier: Development Status :: 5 - Production/Stable
